<annotation>
    <folder>2</folder>
    <filename>image_122.jpg</filename>
    <size>
        <width>1024</width>
        <height>768</height>
        <depth>3</depth>
    </size>
    <object>
        <name>screw</name>
        <difficult>0</difficult>
        <bndbox>
            <xmin>248</xmin>
            <ymin>732</ymin>
            <xmax>292</xmax>
            <ymax>768</ymax>
        </bndbox>
    </object>
    <object>
        <name>screw</name>
        <difficult>0</difficult>
        <bndbox>
            <xmin>399</xmin>
            <ymin>728</ymin>
            <xmax>447</xmax>
            <ymax>768</ymax>
        </bndbox>
    </object>
    <object>
        <name>screw</name>
        <difficult>0</difficult>
        <bndbox>
            <xmin>386</xmin>
            <ymin>41</ymin>
            <xmax>432</xmax>
            <ymax>88</ymax>
        </bndbox>
    </object>
    <object>
        <name>screw</name>
        <difficult>0</difficult>
        <bndbox>
            <xmin>384</xmin>
            <ymin>149</ymin>
            <xmax>433</xmax>
            <ymax>197</ymax>
        </bndbox>
    </object>
    <object>
        <name>screw</name>
        <difficult>0</difficult>
        <bndbox>
            <xmin>391</xmin>
            <ymin>262</ymin>
            <xmax>439</xmax>
            <ymax>309</ymax>
        </bndbox>
    </object>
    <object>
        <name>screw</name>
        <difficult>0</difficult>
        <bndbox>
            <xmin>396</xmin>
            <ymin>377</ymin>
            <xmax>439</xmax>
            <ymax>425</ymax>
        </bndbox>
    </object>
    <object>
        <name>screw</name>
        <difficult>0</difficult>
        <bndbox>
            <xmin>395</xmin>
            <ymin>495</ymin>
            <xmax>443</xmax>
            <ymax>546</ymax>
        </bndbox>
    </object>
    <object>
        <name>screw</name>
        <difficult>0</difficult>
        <bndbox>
            <xmin>395</xmin>
            <ymin>609</ymin>
            <xmax>444</xmax>
            <ymax>663</ymax>
        </bndbox>
    </object>
    <object>
        <name>screw</name>
        <difficult>0</difficult>
        <bndbox>
            <xmin>238</xmin>
            <ymin>613</ymin>
            <xmax>286</xmax>
            <ymax>662</ymax>
        </bndbox>
    </object>
    <object>
        <name>screw</name>
        <difficult>0</difficult>
        <bndbox>
            <xmin>233</xmin>
            <ymin>496</ymin>
            <xmax>283</xmax>
            <ymax>547</ymax>
        </bndbox>
    </object>
    <object>
        <name>screw</name>
        <difficult>0</difficult>
        <bndbox>
            <xmin>231</xmin>
            <ymin>380</ymin>
            <xmax>281</xmax>
            <ymax>435</ymax>
        </bndbox>
    </object>
    <object>
        <name>screw</name>
        <difficult>0</difficult>
        <bndbox>
            <xmin>232</xmin>
            <ymin>263</ymin>
            <xmax>280</xmax>
            <ymax>318</ymax>
        </bndbox>
    </object>
    <object>
        <name>screw</name>
        <difficult>0</difficult>
        <bndbox>
            <xmin>235</xmin>
            <ymin>156</ymin>
            <xmax>281</xmax>
            <ymax>206</ymax>
        </bndbox>
    </object>
    <object>
        <name>screw</name>
        <difficult>0</difficult>
        <bndbox>
            <xmin>230</xmin>
            <ymin>43</ymin>
            <xmax>278</xmax>
            <ymax>93</ymax>
        </bndbox>
    </object>
</annotation>